pubtrend/__init__.py
pubtrend-0.0.0.dist-info/LICENSE
pubtrend-0.0.0.dist-info/METADATA
pubtrend-0.0.0.dist-info/WHEEL
pubtrend-0.0.0.dist-info/top_level.txt
pubtrend-0.0.0.dist-info/RECORD
