Metadata-Version: 2.1
Name: pubtrend
Version: 0.0.0
Summary: Exploring topic trends using biomedical grants and publications
Home-page: https://github.com/rybinmj/pubtrend
Author: Matt Rybin
Author-email: mxr2011@miami.edu
License: UNKNOWN
Platform: UNKNOWN
Classifier: Programming Language :: Python :: 3
Classifier: License :: OSI Approved :: GNU General Public License v3 or later (GPLv3+)
Classifier: Operating System :: OS Independent
Requires-Python: >=3.6
